[
  {
    "id": "v110-dedup-v1-5",
    "title": "v1.10: De-dup v1.5（N-gram 類似 + 正規化）",
    "labels": [
      "roadmap:v1.10",
      "area:quality",
      "area:pipeline"
    ],
    "body": "### Scope\n- N-gram（3-gram）での近似重複KPI\n- 正規化（NFKC/小文字/空白圧縮）\n- **任意ゲート**（`DEDUP_FAIL_THRESHOLD` 設定時のみCIを落とす）\n\n### DoD（v1.10）\n- KPI を Step Summary に常設（pairs/θバケット/topペア）\n- docs/SPEC_DEDUP_V1_5.md に運用記載（日本語）\n- 任意ゲートの導入（デフォルトOFF、値は運用で調整）\n\n### Status\n- **IN PROGRESS**（このチャットでKPI導入済／ゲート追加済）\n### DoD 追加\n- `docs/SPEC_DEDUP_V1_5.md` に**推奨しきい値(0.88)**・Step Summary 例・スケール注意を追記\n- `docs/OPERATIONS_CANDIDATES.md` / `docs/QUALITY_KPIS.md` に **θバケット** と **任意ゲート** を明記\n"
  },
  {
    "id": "v110-notability-v1",
    "title": "v1.10: Notability v1（High/Med/Low=75/20/5）",
    "labels": [
      "roadmap:v1.10",
      "area:quality"
    ],
    "body": "### Scope\n- 特徴量: Apple Popularity / aliases頻度 / 公式フラグ\n- 帯域閾値: 0.67 / 0.33（初期）\n- pick ミックスに適用\n\n### DoD\n- Summary に帯域比\n- SPEC_NOTABILITY.md 反映\n- 直近7日の正答率が 60–85% 帯に入る（観測）",
    "state": "closed"
  },
  {
    "id": "v110-provenance-wire",
    "title": "v1.10: provenance 配線（ingest→pick）",
    "labels": [
      "roadmap:v1.10",
      "area:quality",
      "area:pipeline"
    ],
    "body": "### Scope\n- provenance 最低6項目の欠落なし継承：`source/provider/id/collected_at/hash/license_hint`\n- JSONL/JSON のスキーマ差分棚卸し\n- **stub 既定**の導入（`provider:'stub'`, `id:'stub:'+sha1hex(title|game|answers.canonical)`, `license_hint:'stub'`）\n- **authoring の export 後に fallback を必須適用**\n- **ingest/harvest のアーティファクトは fallback 後のみ保存**\n- 冪等性の保証（同一入力で差分ゼロ）\n\n### Status\n- **DONE**（このチャット）：\n  - candidates（harvest）`with_provenance=100%`\n  - authoring（today）`has_provenance=true / provider=stub / id=stub:<sha1hex…>` を確認\n  - docs（POLICY/SPEC/OPERATIONS）反映済み\n",
    "state": "closed"
  },
  {
    "id": "v110-kpi-summary",
    "title": "v1.10: Step Summary にKPI最小セットを出す",
    "labels": [
      "roadmap:v1.10",
      "area:ops"
    ],
    "body": "### Scope\n- guard/dedup/notability/pick の最小必須セット\n\n### DoD\n- 全主要WFで表示\n- QUALITY_KPIS.md と突合可能",
    "state": "closed"
  },
  {
    "id": "v110-backfill-by-year-if",
    "title": "v1.10: backfill の by_year I/F 設計",
    "labels": [
      "roadmap:v1.10",
      "area:ops"
    ],
    "body": "### Scope\n- public/app/by_year/YYYY.json のI/F確定\n- 未来地平線90日・PR粒度30–90日\n\n### DoD\n- OPERATIONS_BACKFILL.md にI/F例を追記\n- 小規模試験が可能\n### DoD 追加\n- `docs/OPERATIONS_BACKFILL.md` に **JSON Schema 抜粋**・**失敗時フォールバック**・**KPI**・**検証/ドライラン手順** を追記\n"
  },
  {
    "id": "v110-rate-cost-doc",
    "title": "v1.10: Rate/Cost 制御の方針を明文化（任意）",
    "labels": [
      "roadmap:v1.10",
      "area:ops",
      "type:docs"
    ],
    "body": "### Scope\n- レートリミット/バックオフ/キャッシュの指針\n\n### DoD\n- ROADMAP.md および関連 docs に反映"
  }
]
